{
  "$schema": "https://developer.microsoft.com/json-schemas/fabric/item/report/definition/visualContainer/2.4.0/schema.json",
  "name": "0e6467d8d00b9742203d",
  "position": {
    "x": 54.08077321366931,
    "y": 0,
    "z": 29000,
    "height": 57.261995167414561,
    "width": 111.34276838108387,
    "tabOrder": 2000
  },
  "visual": {
    "visualType": "textbox",
    "objects": {
      "general": [
        {
          "properties": {
            "paragraphs": [
              {
                "textRuns": [
                  {
                    "value": "Risco ",
                    "textStyle": {
                      "fontFamily": "Segoe (Bold)",
                      "fontSize": "11pt",
                      "color": "#ffffff"
                    }
                  }
                ]
              },
              {
                "textRuns": [
                  {
                    "value": "Fornecedor",
                    "textStyle": {
                      "fontFamily": "Segoe (Bold)",
                      "fontSize": "11pt",
                      "color": "#ffffff"
                    }
                  }
                ]
              }
            ]
          }
        }
      ]
    },
    "visualContainerObjects": {
      "background": [
        {
          "properties": {
            "show": {
              "expr": {
                "Literal": {
                  "Value": "false"
                }
              }
            }
          }
        }
      ]
    },
    "drillFilterOtherVisuals": true
  },
  "parentGroupName": "f142b087ecd005730a29"
}