{
  "$schema": "https://developer.microsoft.com/json-schemas/fabric/item/report/definition/visualContainer/2.4.0/schema.json",
  "name": "8367ad740b7028fac235",
  "position": {
    "x": 21.401814662594504,
    "y": 324.97878359264496,
    "z": 23000,
    "height": 30.777934936350778,
    "width": 30.777934936350778,
    "tabOrder": 22000
  },
  "visual": {
    "visualType": "image",
    "objects": {
      "general": [
        {
          "properties": {
            "imageUrl": {
              "expr": {
                "ResourcePackageItem": {
                  "PackageName": "RegisteredResources",
                  "PackageType": 1,
                  "ItemName": "tabela_(2)996791287902351.png"
                }
              }
            }
          }
        }
      ]
    },
    "drillFilterOtherVisuals": true
  },
  "howCreated": "InsertVisualButton"
}