{
  "$schema": "https://developer.microsoft.com/json-schemas/fabric/item/report/definition/visualContainer/2.4.0/schema.json",
  "name": "790527c775a2ecb8436c",
  "position": {
    "x": 0,
    "y": 1.6434632321224785,
    "z": 1000,
    "height": 38.314855597223634,
    "width": 38.382748851275409,
    "tabOrder": 14033
  },
  "visual": {
    "visualType": "image",
    "objects": {
      "general": [
        {
          "properties": {
            "imageUrl": {
              "expr": {
                "ResourcePackageItem": {
                  "PackageName": "RegisteredResources",
                  "PackageType": 1,
                  "ItemName": "carteira-de-identidade47755403849889966.png"
                }
              }
            }
          }
        }
      ]
    },
    "drillFilterOtherVisuals": true
  },
  "parentGroupName": "68af7ea96e9a251902b6",
  "howCreated": "InsertVisualButton"
}