{
  "$schema": "https://developer.microsoft.com/json-schemas/fabric/item/report/definition/visualContainer/2.4.0/schema.json",
  "name": "2adcc2d4a0370cc9ea46",
  "position": {
    "x": 1.25,
    "y": 1.25,
    "z": 4000,
    "height": 27.5,
    "width": 38.75,
    "tabOrder": 12002
  },
  "visual": {
    "visualType": "image",
    "objects": {
      "general": [
        {
          "properties": {
            "imageUrl": {
              "expr": {
                "ResourcePackageItem": {
                  "PackageName": "RegisteredResources",
                  "PackageType": 1,
                  "ItemName": "documento_(2)33036743070624874.png"
                }
              }
            }
          }
        }
      ]
    },
    "drillFilterOtherVisuals": true
  },
  "parentGroupName": "74bb46280d00e799b2c3",
  "howCreated": "InsertVisualButton"
}