{
  "$schema": "https://developer.microsoft.com/json-schemas/fabric/item/report/definition/visualContainer/2.4.0/schema.json",
  "name": "17769ba9524d687823bf",
  "position": {
    "x": 192.76400367309458,
    "y": 191.58861340679522,
    "z": 1000,
    "height": 503.06703397612483,
    "width": 1075.4820936639119,
    "tabOrder": 4000
  },
  "visual": {
    "visualType": "calendarVisual5E37BB8CB2CB427ABE4F9EAAE66C5223",
    "query": {
      "queryState": {
        "date": {
          "projections": [
            {
              "field": {
                "Column": {
                  "Expression": {
                    "SourceRef": {
                      "Entity": "Calendário"
                    }
                  },
                  "Property": "Date"
                }
              },
              "queryRef": "Calendário.Date",
              "nativeQueryRef": "Date"
            }
          ]
        },
        "metrics": {
          "projections": [
            {
              "field": {
                "Measure": {
                  "Expression": {
                    "SourceRef": {
                      "Entity": "Gráfico - Calendário"
                    }
                  },
                  "Property": "Quantidade total - contratos"
                }
              },
              "queryRef": "Gráfico - Calendário.Quantidade total - contratos",
              "nativeQueryRef": "Quantidade total - contratos"
            }
          ]
        }
      },
      "sortDefinition": {
        "sort": [
          {
            "field": {
              "Column": {
                "Expression": {
                  "SourceRef": {
                    "Entity": "Calendário"
                  }
                },
                "Property": "Date"
              }
            },
            "direction": "Ascending"
          }
        ],
        "isDefaultSort": true
      }
    },
    "objects": {
      "calendarSettings": [
        {
          "properties": {
            "calendarType": {
              "expr": {
                "Literal": {
                  "Value": "0D"
                }
              }
            },
            "firstDay": {
              "expr": {
                "Literal": {
                  "Value": "0D"
                }
              }
            },
            "cellBorderColor": {
              "solid": {
                "color": {
                  "expr": {
                    "ThemeDataColor": {
                      "ColorId": 1,
                      "Percent": 0
                    }
                  }
                }
              }
            },
            "calendarHeaderColor": {
              "solid": {
                "color": {
                  "expr": {
                    "Literal": {
                      "Value": "'#024873'"
                    }
                  }
                }
              }
            },
            "calendarHeaderTitleColor": {
              "solid": {
                "color": {
                  "expr": {
                    "ThemeDataColor": {
                      "ColorId": 0,
                      "Percent": 0
                    }
                  }
                }
              }
            },
            "weekDayLabelsColor": {
              "solid": {
                "color": {
                  "expr": {
                    "ThemeDataColor": {
                      "ColorId": 1,
                      "Percent": 0
                    }
                  }
                }
              }
            },
            "dayLabelsColor": {
              "solid": {
                "color": {
                  "expr": {
                    "ThemeDataColor": {
                      "ColorId": 1,
                      "Percent": 0
                    }
                  }
                }
              }
            },
            "numOfMonths": {
              "expr": {
                "Literal": {
                  "Value": "12L"
                }
              }
            },
            "cellSize": {
              "expr": {
                "Literal": {
                  "Value": "45L"
                }
              }
            }
          }
        }
      ],
      "metricsSettings": [
        {
          "properties": {
            "metricColor": {
              "solid": {
                "color": {
                  "expr": {
                    "Literal": {
                      "Value": "'#98C483'"
                    }
                  }
                }
              }
            }
          },
          "selector": {
            "metadata": "Gráfico - Calendário.Quantidade total - contratos"
          }
        }
      ]
    },
    "visualContainerObjects": {
      "border": [
        {
          "properties": {
            "show": {
              "expr": {
                "Literal": {
                  "Value": "true"
                }
              }
            },
            "radius": {
              "expr": {
                "Literal": {
                  "Value": "12D"
                }
              }
            },
            "color": {
              "solid": {
                "color": {
                  "expr": {
                    "ThemeDataColor": {
                      "ColorId": 0,
                      "Percent": -0.1
                    }
                  }
                }
              }
            }
          }
        }
      ],
      "dropShadow": [
        {
          "properties": {
            "show": {
              "expr": {
                "Literal": {
                  "Value": "false"
                }
              }
            }
          }
        }
      ],
      "background": [
        {
          "properties": {
            "color": {
              "solid": {
                "color": {
                  "expr": {
                    "Literal": {
                      "Value": "'#ffffff'"
                    }
                  }
                }
              }
            }
          }
        }
      ],
      "title": [
        {
          "properties": {
            "text": {
              "expr": {
                "Literal": {
                  "Value": "'Calendário de Disponibilidade'"
                }
              }
            },
            "alignment": {
              "expr": {
                "Literal": {
                  "Value": "'center'"
                }
              }
            },
            "show": {
              "expr": {
                "Literal": {
                  "Value": "false"
                }
              }
            }
          }
        }
      ]
    },
    "drillFilterOtherVisuals": true
  }
}