{
  "$schema": "https://developer.microsoft.com/json-schemas/fabric/item/report/definition/visualContainer/2.4.0/schema.json",
  "name": "3feb180bb60e2ce28589",
  "position": {
    "x": 183.42488655361834,
    "y": 188.31621686171485,
    "z": 4000,
    "height": 497.69285884881776,
    "width": 577.1769763553857,
    "tabOrder": 3000
  },
  "visual": {
    "visualType": "pivotTable",
    "query": {
      "queryState": {
        "Rows": {
          "projections": [
            {
              "field": {
                "Column": {
                  "Expression": {
                    "SourceRef": {
                      "Entity": "Status de funcionários (Mensal)"
                    }
                  },
                  "Property": "Fornecedor"
                }
              },
              "queryRef": "Status de funcionários (Mensal).Fornecedor",
              "nativeQueryRef": "Fornecedor1",
              "active": true
            },
            {
              "field": {
                "Column": {
                  "Expression": {
                    "SourceRef": {
                      "Entity": "Status de funcionários (Mensal)"
                    }
                  },
                  "Property": "Nome"
                }
              },
              "queryRef": "Status de funcionários (Mensal).Nome",
              "nativeQueryRef": "Nome",
              "active": false
            }
          ]
        },
        "Values": {
          "projections": [
            {
              "field": {
                "Measure": {
                  "Expression": {
                    "SourceRef": {
                      "Entity": "Status de funcionários (Mensal)"
                    }
                  },
                  "Property": "_Documentos_Pendentes"
                }
              },
              "queryRef": "Status de funcionários (Mensal)._Documentos_Pendentes",
              "nativeQueryRef": "Documentos Pendentes",
              "displayName": "Documentos Pendentes"
            }
          ]
        }
      },
      "sortDefinition": {
        "sort": [
          {
            "field": {
              "Column": {
                "Expression": {
                  "SourceRef": {
                    "Entity": "Status de funcionários (Mensal)"
                  }
                },
                "Property": "Fornecedor"
              }
            },
            "direction": "Descending"
          }
        ]
      }
    },
    "expansionStates": [
      {
        "roles": [
          "Rows"
        ],
        "levels": [
          {
            "queryRefs": [
              "Status de funcionários (Mensal).Fornecedor"
            ],
            "isCollapsed": true,
            "identityKeys": [
              {
                "Column": {
                  "Expression": {
                    "SourceRef": {
                      "Entity": "Status de funcionários (Mensal)"
                    }
                  },
                  "Property": "Fornecedor"
                }
              }
            ],
            "isPinned": true
          },
          {
            "queryRefs": [
              "Status de funcionários (Mensal).Nome"
            ],
            "isCollapsed": true,
            "isPinned": true
          }
        ],
        "root": {}
      }
    ],
    "objects": {
      "subTotals": [
        {
          "properties": {
            "columnSubtotals": {
              "expr": {
                "Literal": {
                  "Value": "false"
                }
              }
            },
            "rowSubtotals": {
              "expr": {
                "Literal": {
                  "Value": "false"
                }
              }
            }
          }
        }
      ],
      "columnHeaders": [
        {
          "properties": {
            "fontFamily": {
              "expr": {
                "Literal": {
                  "Value": "'wf_standard-font, helvetica, arial, sans-serif'"
                }
              }
            },
            "fontSize": {
              "expr": {
                "Literal": {
                  "Value": "8D"
                }
              }
            },
            "bold": {
              "expr": {
                "Literal": {
                  "Value": "true"
                }
              }
            },
            "backColor": {
              "solid": {
                "color": {
                  "expr": {
                    "Literal": {
                      "Value": "'#F7F7F7'"
                    }
                  }
                }
              }
            },
            "alignment": {
              "expr": {
                "Literal": {
                  "Value": "'Center'"
                }
              }
            }
          }
        }
      ],
      "values": [
        {
          "properties": {
            "fontFamily": {
              "expr": {
                "Literal": {
                  "Value": "'wf_standard-font, helvetica, arial, sans-serif'"
                }
              }
            },
            "fontSize": {
              "expr": {
                "Literal": {
                  "Value": "8D"
                }
              }
            },
            "bold": {
              "expr": {
                "Literal": {
                  "Value": "false"
                }
              }
            },
            "backColorPrimary": {
              "solid": {
                "color": {
                  "expr": {
                    "Literal": {
                      "Value": "'#F7F7F7'"
                    }
                  }
                }
              }
            },
            "backColorSecondary": {
              "solid": {
                "color": {
                  "expr": {
                    "Literal": {
                      "Value": "'#F7F7F7'"
                    }
                  }
                }
              }
            },
            "valuesOnRow": {
              "expr": {
                "Literal": {
                  "Value": "false"
                }
              }
            }
          }
        }
      ],
      "rowHeaders": [
        {
          "properties": {
            "fontFamily": {
              "expr": {
                "Literal": {
                  "Value": "'wf_standard-font, helvetica, arial, sans-serif'"
                }
              }
            },
            "fontSize": {
              "expr": {
                "Literal": {
                  "Value": "8D"
                }
              }
            },
            "bold": {
              "expr": {
                "Literal": {
                  "Value": "true"
                }
              }
            },
            "backColor": {
              "solid": {
                "color": {
                  "expr": {
                    "Literal": {
                      "Value": "'#F7F7F7'"
                    }
                  }
                }
              }
            },
            "alignment": {
              "expr": {
                "Literal": {
                  "Value": "'Left'"
                }
              }
            }
          }
        }
      ],
      "rowTotal": [
        {
          "properties": {
            "bold": {
              "expr": {
                "Literal": {
                  "Value": "true"
                }
              }
            },
            "backColor": {
              "solid": {
                "color": {
                  "expr": {
                    "ThemeDataColor": {
                      "ColorId": 0,
                      "Percent": -0.1
                    }
                  }
                }
              }
            }
          }
        }
      ],
      "columnWidth": [
        {
          "properties": {
            "value": {
              "expr": {
                "Literal": {
                  "Value": "245.70912461044776D"
                }
              }
            }
          },
          "selector": {
            "metadata": "Status de funcionários.Fornecedor"
          }
        },
        {
          "properties": {
            "value": {
              "expr": {
                "Literal": {
                  "Value": "182.08799482965404D"
                }
              }
            }
          },
          "selector": {
            "metadata": "Status de funcionários (Mensal).Fornecedor"
          }
        },
        {
          "properties": {
            "value": {
              "expr": {
                "Literal": {
                  "Value": "379.1911709678218D"
                }
              }
            }
          },
          "selector": {
            "metadata": "Status de funcionários (Mensal)._Documentos_Pendentes"
          }
        }
      ]
    },
    "visualContainerObjects": {
      "title": [
        {
          "properties": {
            "text": {
              "expr": {
                "Literal": {
                  "Value": "'%Docs Entregues'"
                }
              }
            },
            "titleWrap": {
              "expr": {
                "Literal": {
                  "Value": "true"
                }
              }
            },
            "alignment": {
              "expr": {
                "Literal": {
                  "Value": "'center'"
                }
              }
            },
            "bold": {
              "expr": {
                "Literal": {
                  "Value": "true"
                }
              }
            }
          }
        }
      ],
      "background": [
        {
          "properties": {
            "show": {
              "expr": {
                "Literal": {
                  "Value": "true"
                }
              }
            },
            "color": {
              "solid": {
                "color": {
                  "expr": {
                    "Literal": {
                      "Value": "'#F7F7F7'"
                    }
                  }
                }
              }
            },
            "transparency": {
              "expr": {
                "Literal": {
                  "Value": "0D"
                }
              }
            }
          }
        }
      ],
      "border": [
        {
          "properties": {
            "show": {
              "expr": {
                "Literal": {
                  "Value": "true"
                }
              }
            },
            "color": {
              "solid": {
                "color": {
                  "expr": {
                    "ThemeDataColor": {
                      "ColorId": 0,
                      "Percent": -0.1
                    }
                  }
                }
              }
            },
            "radius": {
              "expr": {
                "Literal": {
                  "Value": "12D"
                }
              }
            }
          }
        }
      ],
      "dropShadow": [
        {
          "properties": {
            "show": {
              "expr": {
                "Literal": {
                  "Value": "false"
                }
              }
            }
          }
        }
      ]
    },
    "drillFilterOtherVisuals": true
  }
}